LICENSE
MANIFEST.in
README.md
requirements.txt
setup.py
toycv/__init__.py
toycv/benchmark.py
toycv/common.py
toycv/metrics.py
toycv/string.py
toycv.egg-info/PKG-INFO
toycv.egg-info/SOURCES.txt
toycv.egg-info/dependency_links.txt
toycv.egg-info/requires.txt
toycv.egg-info/top_level.txt
toycv/file/__init__.py
toycv/file/image.py
toycv/file/path.py
toycv/pytorch/__init__.py
toycv/pytorch/datasets.py
toycv/pytorch/models.py
toycv/pytorch/transform.py
toycv/visualization/__init__.py